datasette_secrets/__init__.py
datasette_secrets/hookspecs.py
datasette_secrets/templates/secrets_index.html
datasette_secrets/templates/secrets_update.html
datasette_secrets-0.2.dist-info/LICENSE
datasette_secrets-0.2.dist-info/METADATA
datasette_secrets-0.2.dist-info/WHEEL
datasette_secrets-0.2.dist-info/entry_points.txt
datasette_secrets-0.2.dist-info/top_level.txt
datasette_secrets-0.2.dist-info/RECORD
