Metadata-Version: 2.1
Name: datasette-secrets
Version: 0.2
Summary: Manage secrets such as API keys for use with other Datasette plugins
Author: Datasette
License: Apache-2.0
Project-URL: Homepage, https://github.com/datasette/datasette-secrets
Project-URL: Changelog, https://github.com/datasette/datasette-secrets/releases
Project-URL: Issues, https://github.com/datasette/datasette-secrets/issues
Project-URL: CI, https://github.com/datasette/datasette-secrets/actions
Classifier: Framework :: Datasette
Classifier: License :: OSI Approved :: Apache Software License
Requires-Python: >=3.8
License-File: LICENSE
Requires-Dist: datasette
Requires-Dist: cryptography
Provides-Extra: test
Requires-Dist: pytest ; extra == 'test'
Requires-Dist: pytest-asyncio ; extra == 'test'
Requires-Dist: datasette-test >=0.3.2 ; extra == 'test'
